LICENSE.txt
setup.py
Rawan_aq11.egg-info/PKG-INFO
Rawan_aq11.egg-info/SOURCES.txt
Rawan_aq11.egg-info/dependency_links.txt
Rawan_aq11.egg-info/top_level.txt
code/__init__.py