Metadata-Version: 2.1
Name: Rawan-aq11
Version: 0.1
Summary: simble calculator 
Author: Rawan aqlan
License-File: LICENSE.txt
